{
    "name": "root",
    "metadata": {
        "timer_format_version": "0.1.0",
        "start_time_seconds": "1759796404",
        "python_version": "3.9.13 (tags/v3.9.13:6de2ca5, May 17 2022, 16:36:42) [MSC v.1929 64 bit (AMD64)]",
        "command_line_arguments": "C:\\Users\\sxea7\\mlagents-env\\Scripts\\mlagents-learn config/trainer_config.yaml --run-id=EndlessRunner_001 --force",
        "mlagents_version": "0.30.0",
        "mlagents_envs_version": "0.30.0",
        "communication_protocol_version": "1.5.0",
        "pytorch_version": "2.8.0+cpu",
        "numpy_version": "1.21.2",
        "end_time_seconds": "1759796436"
    },
    "total": 32.2690463,
    "count": 1,
    "self": 0.00800490000000309,
    "children": {
        "run_training.setup": {
            "total": 0.17198669999999971,
            "count": 1,
            "self": 0.17198669999999971
        },
        "TrainerController.start_learning": {
            "total": 32.0890547,
            "count": 1,
            "self": 0.0005199000000004617,
            "children": {
                "TrainerController._reset_env": {
                    "total": 32.0885226,
                    "count": 1,
                    "self": 32.0885226
                },
                "trainer_threads": {
                    "total": 9.999999974752427e-07,
                    "count": 1,
                    "self": 9.999999974752427e-07
                },
                "TrainerController._save_models": {
                    "total": 1.1200000002986599e-05,
                    "count": 1,
                    "self": 1.1200000002986599e-05
                }
            }
        }
    }
}